jackrecorder/__init__.py
jackrecorder/recorder.py
jackrecorder-0.0.2.data/scripts/recorder
jackrecorder-0.0.2.dist-info/LICENSE
jackrecorder-0.0.2.dist-info/METADATA
jackrecorder-0.0.2.dist-info/WHEEL
jackrecorder-0.0.2.dist-info/top_level.txt
jackrecorder-0.0.2.dist-info/RECORD
